getswish/__init__.py
getswish/client.py
getswish/environments.py
getswish/exceptions.py
getswish/models.py
getswish/utils.py
getswish-0.3.0.dist-info/licenses/LICENSE
getswish-0.3.0.dist-info/WHEEL
getswish-0.3.0.dist-info/METADATA
getswish-0.3.0.dist-info/RECORD
