Metadata-Version: 2.4
Name: getswish
Version: 0.3.0
Summary: Getswish python client library
Keywords: swish,getswish,payment,payout
Author-email: Daniel Nibon <daniel@nibon.se>
Requires-Python: >=3.10
Classifier: Intended Audience :: Developers
Classifier: License :: OSI Approved :: MIT License
Classifier: Programming Language :: Python :: 3
Classifier: Topic :: Software Development :: Libraries :: Python Modules
License-File: LICENSE
Requires-Dist: requests >= 2.27
Requires-Dist: rsa >= 4.7.2
Requires-Dist: flit >= 3.8 ; extra == "deploy"
Requires-Dist: pytest >= 7 ; extra == "tests"
Requires-Dist: pytest-mock ; extra == "tests"
Requires-Dist: pytest-cov >= 4 ; extra == "tests"
Requires-Dist: ruff ; extra == "tests"
Requires-Dist: nox ; extra == "tests"
Project-URL: Source, https://github.com/nibon/getswish-python
Provides-Extra: deploy
Provides-Extra: tests
